ahgregate/__init__.py
ahgregate/_version.py
ahgregate/scripts.py
ahgregate/test.py
ahgregate/workers.py
ahgregate-0.1.2.dist-info/LICENSE
ahgregate-0.1.2.dist-info/METADATA
ahgregate-0.1.2.dist-info/WHEEL
ahgregate-0.1.2.dist-info/entry_points.txt
ahgregate-0.1.2.dist-info/top_level.txt
ahgregate-0.1.2.dist-info/RECORD
