Metadata-Version: 2.1
Name: ahgregate
Version: 0.1.2
Summary: Command line and other utilties for aggregate.
Author-email: "Stephen J. Mildenhall" <steve@convexrisk.com>
Maintainer-email: "Stephen J. Mildenhall" <steve@convexrisk.com>
License: BSD-3-Clause
Project-URL: Documentation, https://ahgregate.readthedocs.io/en/latest/
Project-URL: Source Code, https://github.com/mynl/ahgregate
Classifier: Development Status :: 4 - Beta
Classifier: Intended Audience :: Education
Classifier: Intended Audience :: Financial and Insurance Industry
Classifier: License :: OSI Approved :: BSD License
Classifier: Programming Language :: Python :: 3
Classifier: Programming Language :: Python :: 3.10
Classifier: Topic :: Education
Classifier: Topic :: Office/Business :: Financial
Classifier: Topic :: Scientific/Engineering :: Mathematics
Requires-Python: >=3.10
License-File: LICENSE
Requires-Dist: aggregate
Requires-Dist: IPython
Requires-Dist: click
Requires-Dist: ipykernel
Requires-Dist: jinja2
Requires-Dist: matplotlib (>=3.5)
Requires-Dist: numpy
Requires-Dist: pandas
Requires-Dist: psutil
Requires-Dist: scipy
Provides-Extra: dev
Requires-Dist: docutils (==0.16) ; extra == 'dev'
Requires-Dist: jupyter-sphinx ; extra == 'dev'
Requires-Dist: nbsphinx ; extra == 'dev'
Requires-Dist: recommonmark (>=0.7.1) ; extra == 'dev'
Requires-Dist: setuptools (>=62.3.2) ; extra == 'dev'
Requires-Dist: sphinx (>=1.4) ; extra == 'dev'
Requires-Dist: sphinx-panels ; extra == 'dev'
Requires-Dist: sphinx-rtd-dark-mode ; extra == 'dev'
Requires-Dist: sphinxcontrib-bibtex ; extra == 'dev'
Requires-Dist: sphinx-copybutton ; extra == 'dev'
Requires-Dist: sphinx-toggleprompt ; extra == 'dev'
Requires-Dist: sphinx-multitoc-numbering ; extra == 'dev'
